MANIFEST.in
README.rst
setup.py
megaplanpy/__init__.py
megaplanpy/client.py
megaplanpy/data.py
megaplanpy/main.py
megaplanpy.egg-info/PKG-INFO
megaplanpy.egg-info/SOURCES.txt
megaplanpy.egg-info/dependency_links.txt
megaplanpy.egg-info/not-zip-safe
megaplanpy.egg-info/top_level.txt