Metadata-Version: 1.0
Name: megaplanpy
Version: 0.11.04
Summary: UNKNOWN
Home-page: https://github.com/pikhovkin/megaplanpy/
Author: Sergey Pikhovkin
Author-email: s@pikhovkin.ru
License: MIT
Keywords: megaplan api
Platform: UNKNOWN
Classifier: Development Status :: 2 - Pre-Alpha
Classifier: Intended Audience :: Developers
Classifier: License :: OSI Approved :: MIT License
Classifier: Environment :: Web Environment
Classifier: Natural Language :: Russian
Classifier: Natural Language :: English
Classifier: Operating System :: OS Independent
Classifier: Programming Language :: Python
Classifier: Topic :: Software Development :: Libraries :: Python Modules
